nora_lib/__init__.py
nora_lib/py.typed
nora_lib/serializers.py
nora_lib/progress/__init__.py
nora_lib/progress/models.py
nora_lib/progress/reporter.py
nora_lib/tasks/__init__.py
nora_lib/tasks/models.py
nora_lib/tasks/state.py
nora_lib-1.8.2.dist-info/METADATA
nora_lib-1.8.2.dist-info/WHEEL
nora_lib-1.8.2.dist-info/top_level.txt
nora_lib-1.8.2.dist-info/RECORD
