Metadata-Version: 2.4
Name: nora_lib
Version: 1.8.2
Summary: For making and coordinating agents and tools
Home-page: https://github.com/allenai/nora_lib/interface
Requires-Python: >=3.9
Requires-Dist: pydantic<3,>=2
Provides-Extra: dev
Requires-Dist: mypy; extra == "dev"
Requires-Dist: pytest; extra == "dev"
Requires-Dist: black; extra == "dev"
Dynamic: home-page
Dynamic: provides-extra
Dynamic: requires-dist
Dynamic: requires-python
Dynamic: summary
